github/__init__.py
github/cache.py
github/client.py
github/exceptions.py
github/http.py
github/objects.py
github/urls.py
github_python-1.2.3.dist-info/LICENSE
github_python-1.2.3.dist-info/METADATA
github_python-1.2.3.dist-info/WHEEL
github_python-1.2.3.dist-info/top_level.txt
github_python-1.2.3.dist-info/RECORD
