Metadata-Version: 2.1
Name: github-python
Version: 1.2.3
Summary: An asynchronous python wrapper around the GitHub API
Home-page: https://github.com/VarMonke/Github-Api-Wrapper
Author: VarMonke & sudosnok
Author-email: var.monke@gmail.com
License: MIT
Project-URL: Issue Tracker, https://github.com/VarMonke/Github-Api-Wrapper/issues
Platform: any
Requires-Python: >=3.8.0
License-File: LICENSE
Requires-Dist: aiohttp (==3.8.1)
Requires-Dist: typing-extensions
